Metadata-Version: 2.1
Name: oneNeuron-pkg-Django-Blockchained
Version: 0.0.5
Summary: A small package for perceptron
Home-page: https://github.com/Django-Blockchained/Perceptron-package
Author: Django-Blockchained
Author-email: vishalp7711@gmail.com
Project-URL: Bug Tracker, https://github.com/Django-Blockchained/Perceptron-package/issues
Classifier: Programming Language :: Python :: 3
Classifier: License :: OSI Approved :: MIT License
Classifier: Operating System :: OS Independent
Requires-Python: >=3.6
License-File: LICENSE
Requires-Dist: numpy (==1.21.4)
Requires-Dist: pandas (==1.3.4)
Requires-Dist: joblib (==1.1.0)
